{
  "Certificate": {
    "Name": "AWS::IoT::Certificate",
    "Properties": {
      "CertificateSigningRequest": {
        "Description": "",
        "Array": false,
        "Type": "String",
        "UpdateRequires": "Replacement"
      },
      "Status": {
        "Description": "",
        "Array": false,
        "Type": "String",
        "UpdateRequires": "No interruption"
      },
      "Arn": {
        "Description": "A value similar to the following is\n                     returned:",
        "Array": false,
        "Type": "String"
      }
    }
  },
  "Thing": {
    "Name": "AWS::IoT::Thing",
    "Properties": {
      "AttributePayload": {
        "Description": "",
        "Array": false,
        "Type": "String",
        "UpdateRequires": "No interruption"
      },
      "ThingName": {
        "Description": "",
        "Array": false,
        "Type": "String",
        "UpdateRequires": "Replacement"
      }
    }
  },
  "ThingPrincipalAttachment": {
    "Name": "AWS::IoT::ThingPrincipalAttachment",
    "Properties": {
      "Principal": {
        "Description": "",
        "Array": false,
        "Type": "String",
        "UpdateRequires": "Replacement"
      },
      "ThingName": {
        "Description": "",
        "Array": false,
        "Type": "String",
        "UpdateRequires": "Replacement"
      }
    }
  },
  "Policy": {
    "Name": "AWS::IoT::Policy",
    "Properties": {
      "PolicyDocument": {
        "Description": "",
        "Array": false,
        "Type": "String",
        "UpdateRequires": "Replacement"
      },
      "PolicyName": {
        "Description": "",
        "Array": false,
        "Type": "String",
        "UpdateRequires": "Replacement"
      }
    }
  },
  "PolicyPrincipalAttachment": {
    "Name": "AWS::IoT::PolicyPrincipalAttachment",
    "Properties": {
      "PolicyName": {
        "Description": "",
        "Array": false,
        "Type": "String",
        "UpdateRequires": "Replacement"
      },
      "Principal": {
        "Description": "",
        "Array": false,
        "Type": "String",
        "UpdateRequires": "Replacement"
      }
    }
  },
  "TopicRule": {
    "Name": "AWS::IoT::TopicRule",
    "Properties": {
      "RuleName": {
        "Description": "",
        "Array": false,
        "Type": "String",
        "UpdateRequires": "Replacement"
      },
      "TopicRulePayload": {
        "Description": "",
        "Array": false,
        "Type": "String",
        "UpdateRequires": "No interruption"
      }
    }
  }
}
