{
  "Workspace": {
    "Name": "AWS::WorkSpaces::Workspace",
    "Properties": {
      "BundleId": {
        "Description": "",
        "Array": false,
        "Type": "String",
        "UpdateRequires": "Updates are not supported.. To update this property, you must also update another\n                  property that triggers a replacement, such as the UserName\n                  property."
      },
      "DirectoryId": {
        "Description": "",
        "Array": false,
        "Type": "String",
        "UpdateRequires": "Replacement"
      },
      "UserName": {
        "Description": "",
        "Array": false,
        "Type": "String",
        "UpdateRequires": "Replacement"
      },
      "RootVolumeEncryptionEnabled": {
        "Description": "",
        "Array": false,
        "Type": "String",
        "UpdateRequires": "Updates are not supported.. To update this property, you must also update another\n                  property that triggers a replacement, such as the UserName\n                  property."
      },
      "UserVolumeEncryptionEnabled": {
        "Description": "",
        "Array": false,
        "Type": "String",
        "UpdateRequires": "Updates are not supported.. To update this property, you must also update another\n                  property that triggers a replacement, such as the UserName\n                  property."
      },
      "VolumeEncryptionKey": {
        "Description": "",
        "Array": false,
        "Type": "String",
        "UpdateRequires": "Updates are not supported.. To update this property, you must also update another\n                  property that triggers a replacement, such as the UserName\n                  property."
      }
    }
  }
}
